[{"1":{"Kind":1}},{"1":{"Kind":2}},{"1":{"Kind":3}},{"1":{"Kind":4}},{"1":{"Kind":5}},{"1":{"Kind":6}},{"1":{"Kind":7}},{"1":{"Kind":8}},{"6":{"Value":"Lease"}},{"6":{"Value":"coordination.k8s.io/v1beta1"}},{"2":{"Name":"labels","Properties":{},"AdditionalProperties":4}},{"2":{"Name":"annotations","Properties":{},"AdditionalProperties":4}},{"2":{"Name":"metadata","Properties":{"name":{"Type":4,"Flags":9,"Description":"The name of the resource."},"namespace":{"Type":4,"Flags":8,"Description":"The namespace of the resource."},"labels":{"Type":10,"Flags":0,"Description":"The labels for the resource."},"annotations":{"Type":11,"Flags":0,"Description":"The annotations for the resource."}}}},{"2":{"Name":"IoK8SApiCoordinationV1Beta1LeaseSpec","Properties":{"acquireTime":{"Type":4,"Flags":0,"Description":"MicroTime is version of Time with microsecond level precision."},"holderIdentity":{"Type":4,"Flags":0,"Description":"holderIdentity contains the identity of the holder of a current lease."},"leaseDurationSeconds":{"Type":3,"Flags":0,"Description":"leaseDurationSeconds is a duration that candidates for a lease need to wait to force acquire it. This is measure against time of last observed RenewTime."},"leaseTransitions":{"Type":3,"Flags":0,"Description":"leaseTransitions is the number of transitions of a lease between holders."},"renewTime":{"Type":4,"Flags":0,"Description":"MicroTime is version of Time with microsecond level precision."}}}},{"2":{"Name":"kubernetes.coordination.k8s.io/Lease","Properties":{"kind":{"Type":8,"Flags":10,"Description":"The resource kind."},"apiVersion":{"Type":9,"Flags":10,"Description":"The api version."},"metadata":{"Type":12,"Flags":1,"Description":"The resource metadata."},"spec":{"Type":13,"Flags":0,"Description":"LeaseSpec is a specification of a Lease."}}}},{"4":{"Name":"kubernetes.coordination.k8s.io/Lease@v1beta1","ScopeType":0,"Body":14}}]